{
  "slug": "remotion-best-practices",
  "name": "remotion-best-practices",
  "publisher": "remotion-dev",
  "source_repo": "https://github.com/remotion-dev/skills",
  "skills_sh_url": "https://skills.sh/remotion-dev/skills/remotion-best-practices",
  "install_count_skills_sh": 299613,
  "license": "MIT",
  "description": "Best practices for programmatic video generation with Remotion.",
  "fires_when": "",
  "skill_md_content": "",
  "skill_md_url": "",
  "skill_md_size_bytes": 0,
  "files": [],
  "fetched_at": ""
}
